qc2plus/.DS_Store
qc2plus/__init__.py
qc2plus/cli.py
qc2plus/alerting/alerts.py
qc2plus/core/.DS_Store
qc2plus/core/connection.py
qc2plus/core/project.py
qc2plus/core/runner.py
qc2plus/level1/engine.py
qc2plus/level1/macros.py
qc2plus/level1/utils.py
qc2plus/level2/README.md
qc2plus/level2/anomaly_filter.py
qc2plus/level2/correlation.py
qc2plus/level2/distribution.py
qc2plus/level2/temporal.py
qc2plus/persistence/persistence.py
qc2plus/sql/__init__.py
qc2plus/sql/db_functions.py
qc2plus-1.0.0.dist-info/licenses/LICENSE
qc2plus-1.0.0.dist-info/METADATA
qc2plus-1.0.0.dist-info/WHEEL
qc2plus-1.0.0.dist-info/entry_points.txt
qc2plus-1.0.0.dist-info/top_level.txt
qc2plus-1.0.0.dist-info/RECORD
