Metadata-Version: 2.4
Name: qc2plus
Version: 1.0.0
Summary: Data Quality Automation Framework with ML-powered anomaly detection
Home-page: https://github.com/kheopsys/qc2plus-internal
Author: QC2Plus Team
Author-email: QC2Plus Team <contact-qc2plus@kheopsys.com>
License: MIT
Project-URL: Homepage, https://github.com/kheopsys/qc2plus-internal
Project-URL: Documentation, https://github.com/kheopsys/qc2plus-internal/README.md
Project-URL: Bug Reports, https://github.com/kheopsys/qc2plus-internal/issues
Project-URL: Source, https://github.com/kheopsys/qc2plus-internal
Keywords: data-quality,sql,ml,anomaly-detection,dbt-like
Classifier: Development Status :: 4 - Beta
Classifier: Intended Audience :: Developers
Classifier: Topic :: Database
Classifier: Topic :: Software Development :: Quality Assurance
Classifier: License :: OSI Approved :: MIT License
Classifier: Programming Language :: Python :: 3
Classifier: Programming Language :: Python :: 3.9
Classifier: Programming Language :: Python :: 3.10
Classifier: Programming Language :: Python :: 3.11
Requires-Python: >=3.9
License-File: LICENSE
Requires-Dist: sqlalchemy>=1.4.0
Requires-Dist: pandas>=1.3.0
Requires-Dist: pyyaml>=5.4.0
Requires-Dist: numpy>=1.21.0
Requires-Dist: scipy>=1.7.0
Requires-Dist: scikit-learn>=1.0.0
Provides-Extra: bigquery
Requires-Dist: sqlalchemy-bigquery>=1.4.0; extra == "bigquery"
Provides-Extra: snowflake
Requires-Dist: snowflake-sqlalchemy>=1.4.0; extra == "snowflake"
Provides-Extra: dev
Requires-Dist: pytest>=7.0.0; extra == "dev"
Requires-Dist: black>=22.0.0; extra == "dev"
Requires-Dist: flake8>=4.0.0; extra == "dev"
Dynamic: author
Dynamic: home-page
Dynamic: license-file
Dynamic: requires-python
